app/__init__.py
app/asgi.py
app/config.py
app/files.py
app/job.py
app/logger.py
app/setup.py
app/utils.py
app/cli/__init__.py
app/cli/__main__.py
app/cli/classes.py
app/cli/profile.py
app/cli/jobs/__init__.py
app/cli/jobs/speech_recognition.py
app/cli/services/__init__.py
app/cli/services/speech_recognition.py
app/cli/services/text_generation.py
app/db/migrations/__init__.py
app/db/migrations/alembic.ini
app/db/migrations/env.py
app/db/migrations/script.py.mako
app/db/migrations/versions/2024-10-29_v0_1_1_cd82a755baba.py
app/db/migrations/versions/2024-11-02_add_model_model_dir_2df28a56f27b.py
app/db/migrations/versions/2025-01-22_make_scheduler_and_provider_optional_4e499534bca6.py
app/db/migrations/versions/2025-01-22_test_refactoring_caf49b326612.py
app/db/migrations/versions/2025-06-17_create_batch_jobs_4dfd6eed368a.py
app/db/migrations/versions/2025-06-30_add_service_job_resources_024848c488c2.py
app/db/migrations/versions/2025-09-19_add_job_account_27b628a63d4e.py
app/db/migrations/versions/__init__.py
app/jobs/__init__.py
app/jobs/base.py
app/jobs/speech_recognition.py
app/models/__init__.py
app/models/model.py
app/models/profile.py
app/services/__init__.py
app/services/base.py
app/services/speech_recognition.py
app/services/text_generation.py
app/templates/base_local.sh
app/templates/base_slurm.sh
app/templates/speech_recognition_local.sh
app/templates/speech_recognition_slurm.sh
app/templates/text_generation_local.sh
app/templates/text_generation_slurm.sh
app/templates/deprecated/text_generation_local.sh
app/templates/deprecated/text_generation_slurm.sh
app/templates/jobs/speech_recognition_local.sh
app/templates/jobs/speech_recognition_slurm.sh
blackfish_ai-0.3.0.dist-info/METADATA
blackfish_ai-0.3.0.dist-info/WHEEL
blackfish_ai-0.3.0.dist-info/entry_points.txt
blackfish_ai-0.3.0.dist-info/licenses/LICENSE
blackfish_ai-0.3.0.dist-info/RECORD
